{
  "$schema": "https://ui-v4-livid.vercel.app/schema/registry-item.json",
  "name": "rich-editor-readonly-demo",
  "type": "registry:example",
  "registryDependencies": [
    "rich-editor"
  ],
  "files": [
    {
      "path": "registry/new-york-v4/examples/rich-editor-readonly-demo.tsx",
      "content": "\"use client\"\n\nimport { EditorProvider } from \"../ui/rich-editor\"\nimport type { ContainerNode } from \"../ui/rich-editor\"\nimport { createDemoContent } from \"../ui/rich-editor/demo-content\"\nimport { Editor } from \"../ui/rich-editor/editor\"\n\nexport default function RichEditorReadonlyDemo() {\n  const initialContainer: ContainerNode = {\n    id: \"root\",\n    type: \"container\",\n    children: createDemoContent(),\n    attributes: {},\n  }\n\n  return (\n    <div className=\"mx-auto w-full overflow-y-auto\">\n      <EditorProvider initialContainer={initialContainer}>\n        <Editor readOnly notionBased />\n      </EditorProvider>\n    </div>\n  )\n}\n",
      "type": "registry:example"
    }
  ]
}